Workbook

Sheet Matriz Ckeck LIst
C3: MATRIZ PARA COMPROBACIÓN REQUERIMIENTOS DE CALIDAD DE PROYECTO ACADEMICO
D5: SISTEMA: | E5: SISTEMA DE GESTION DE CRIANZA DE CONEJOS (Hoptolt)
F6: Requerimientos Funcionales
B7: Nº | C7: CRITERIOS DE CALIDAD (Documento/Requerimientos) | E7: Status Nivel de Acuerdo | F7: 10.1 Módulo Usuarios y Autenticación | I7: 10.2 Módulo Productos | J7: Status Nivel de Acuerdo | K7: 10.3 Módulo Canchas
B9: 1 | C9: Agreed | E9: NOK | F9: 1. No se presenta evidencia de aceptación formal de los requisitos mediante acta, minuta o validación del cliente. 2. Se requiere evidencia de aprobación de los RF-001 al RF-006 por parte del cliente o responsable del proyecto. | G9: NOK | I9: No se presenta evidencia de aceptación formal de los requisitos RF-007 al RF-015 mediante acta, minuta o validación documentada del cliente. | J9: NOK | K9: No se presenta evidencia de aceptación formal de los requisitos RF-016 al RF-020 mediante acta, minuta o validación documentada del cliente o responsable del proyecto.
B10: 2 | C10: Ranked | E10: OK | F10: 1. Los requisitos RF-001, RF-002, RF-003 y RF-004 tienen prioridad Alta. 2. Los requisitos RF-005 y RF-006 tienen prioridad Media. 3. Cada requisito cuenta con una prioridad definida. | G10: OK | I10: Los requisitos RF-007, RF-008, RF-009 y RF-010 tienen prioridad Alta. Los requisitos RF-011, RF-012, RF-013, RF-014 y RF-015 tienen prioridad Media. | J10: OK | K10: Los requisitos RF-016, RF-017 y RF-018 tienen prioridad Alta. Los requisitos RF-019 y RF-020 tienen prioridad Media. Cada requisito cuenta con un nivel de prioridad definido.
B11: 3 | C11: Unambiguos | E11: OK | F11: 1. Los requisitos están redactados en lenguaje claro y específico. 2. Los criterios de aceptación establecen condiciones concretas para determinar cuándo se cumple cada requisito. 3. No se identifican interpretaciones contradictorias en la descripción de los RF-001 al RF-006. | G11: OK | I11: Los requisitos describen de forma clara las funciones de registro, modificación, consulta y desactivación de productos, así como la gestión de inventario y categorías. | J11: OK | K11: Los requisitos describen de forma clara las funciones de registro, modificación, consulta de disponibilidad y deshabilitación de canchas, así como la alerta de tiempo límite de reserva activa. Los criterios de aceptación establecen condiciones operativas y restricciones cuantitativas específicas (5 s, 3 s, 10 min) que evitan interpretaciones subjetivas o ambiguas.
B12: 4 | C12: Valid and up-to date | E12: NOK | F12: 1. No se presenta evidencia que permita comprobar que todos los requisitos corresponden a la versión más reciente aprobada por el cliente. 2. Se requiere verificar que los RF-001 al RF-006 incorporen los últimos cambios solicitados durante la revisión del proyecto. | G12: NOK | I12: No se presenta evidencia suficiente para comprobar que los requisitos RF-007 al RF-015 corresponden a la última versión aprobada por el cliente. | J12: NOK | K12: No se presenta evidencia suficiente para comprobar que los requisitos RF-016 al RF-020 corresponden a la última versión aprobada por el cliente. Se requiere verificar que las reglas de tarifas futuras y estados de canchas incorporen los últimos cambios solicitados durante la revisión del proyecto.
B13: 5 | C13: Correct | E13: OK | F13: 1. Los requisitos describen funcionalidades propias del módulo de Usuarios y Autenticación. 2. Las funcionalidades definidas, como registro, autenticación, asignación de roles, control de acceso, cierre de sesión y recuperación de contraseña, son coherentes con el propósito del módulo. 3. Los criterios de aceptación especifican el comportamiento esperado del sistema. | G13: OK | I13: Los requisitos describen funcionalidades propias del Módulo Productos del sistema Canchas Don Pepito. Las funciones definidas son coherentes con la gestión de productos, categorías e inventario de la tienda del complejo deportivo. | J13: OK | K13: Los requisitos describen funcionalidades propias del Módulo Canchas del sistema Canchas Don Pepito. Las funciones definidas son coherentes con la administración del catálogo de canchas, control de tarifas por hora, horarios de atención, verificación visual de disponibilidad y gestión de alertas operativas para el personal.
B14: 6 | C14: Consisten | E14: OK | F14: 1. Los requisitos utilizan de manera consistente los conceptos de usuario, cliente, vendedor, administrador, rol, sesión y contraseña. 2. No existen contradicciones entre los RF-001 al RF-006. 3. La asignación de roles definida en RF-003 es utilizada como base para la restricción de acceso establecida en RF-004. | G14: OK | I14: 1, Los requisitos utilizan de forma consistente los conceptos de producto, categoría, inventario, stock y administrador. 2. La asignación de categorías definida en RF-014 complementa el registro de productos establecido en RF-007. 3. La actualización de inventario de RF-008 y la alerta de stock mínimo de RF-011 mantienen una relación funcional coherente con la administración de existencias. 4. La desactivación lógica de RF-012 permite conservar los productos en el historial sin mantenerlos disponibles en el catálogo del cliente. | J14: OK | K14: 1. Los requisitos utilizan de forma consistente los conceptos de cancha, tipo de cancha, tarifa por hora, horario de atención, estado de disponibilidad y reserva activa. 2. La modificación de cancha de RF-017 y la deshabilitación lógica de RF-019 complementan el catálogo visible al cliente. 3. Se establece de forma no contradictoria que el cambio de tarifa o deshabilitación no altera las reservas ya confirmadas o pagadas, aplicándose únicamente a futuras reservas. 4. La consulta de disponibilidad en calendario (RF-018) y la alerta de tiempo límite (RF-020) mantienen una relación funcional coherente con el módulo de reservas.
B15: 7 | C15: Verifiable | E15: NOK | F15: 1. Los requisitos cuentan con criterios de aceptación medibles y comprobables. 2. RF-002 establece valores verificables: 5 intentos fallidos y 5 minutos de bloqueo. 3. RF-004 establece como condición verificable el rechazo del 100 % de intentos de acceso no autorizados. 4. RF-006 establece un tiempo máximo de 30 minutos para la validez del enlace de recuperación. | G15: OK | I15: 1. Los requisitos cuentan con criterios de aceptación que permiten definir pruebas verificables. 2. RF-007 establece validaciones para los campos obligatorios, el formato del precio y la duplicidad del nombre dentro de una misma categoría. 3. RF-008 establece la actualización del stock en menos de 2 segundos y contempla el control de ventas concurrentes. 4. RF-009 establece un tiempo máximo de 5 segundos para reflejar los cambios en el catálogo; RF-010 establece un tiempo inferior a 3 segundos para las consultas paginadas. 5. RF-011 establece un tiempo máximo de 1 minuto para generar la alerta de stock mínimo. | J15: OK | K15: 1. Los requisitos cuentan con criterios de aceptación que permiten definir pruebas verificables y medibles. 2. RF-016 establece validaciones para los campos obligatorios (nombre, tipo, tarifa por hora, horario de atención y estado inicial). 3. RF-017 establece un tiempo máximo de 5 segundos para reflejar los cambios en el catálogo del cliente y valida la protección de reservas confirmadas. 4. RF-018 establece una latencia menor o igual a 3 segundos para la actualización del calendario visual tras cualquier cambio de estado. 5. RF-019 establece el retiro inmediato del catálogo ante deshabilitación y notificación a clientes con reservas futuras. 6. RF-020 establece el disparo automático de la alerta a los 10 minutos restantes con un margen de error menor a 30 segundos y recuperación tras restablecimiento de conexión.
B16: 8 | C16: Realizable | E16: OK | F16: 1. Las funcionalidades descritas corresponden a funciones técnicamente implementables en un sistema de autenticación. 2. Los requisitos establecen reglas concretas para registro, autenticación, autorización y recuperación de credenciales. 3. No se identifican condiciones que hagan técnicamente inviable la implementación de las funcionalidades descritas. | G16: OK | I16: Las funcionalidades descritas corresponden a operaciones técnicamente implementables en un sistema de gestión de productos e inventario. Los requisitos definen reglas concretas para el registro y modificación de productos, el control de existencias, la administración de categorías y la desactivación lógica. | J16: OK | K16: Las funcionalidades descritas corresponden a operaciones técnicamente implementables en un sistema web responsivo y móvil con backend de gestión de reservas. Los requisitos definen reglas de negocio concretas para el registro, edición, deshabilitación de canchas, consulta visual en calendario y temporizadores de reservas activas.
B17: 9 | C17: Traceable | E17: OK | F17: 1. Cada requisito posee un identificador único: RF-001, RF-002, RF-003, RF-004, RF-005 y RF-006. 2. Los requisitos pueden relacionarse con funcionalidades específicas del módulo Usuarios y Autenticación. 3. Los criterios de aceptación permiten establecer posteriormente casos de prueba asociados a cada requisito. | G17: OK | I17: Cada requisito posee un identificador único, desde RF-007 hasta RF-015. Los identificadores y criterios de aceptación permiten establecer posteriormente la relación con los casos de prueba correspondientes | J17: OK | K17: 1. Cada requisito posee un identificador único normalizado: RF-016, RF-017, RF-018, RF-019 y RF-020. 2. Los requisitos mantienen trazabilidad bidireccional directa con los casos de uso: RF-016 con GRC-23 (Ingresar Cancha), RF-017 con GRC-24 (Modificar Cancha), RF-018 con GRC-25 (Consultar Disponibilidad Cancha), RF-019 con GRC-26 (Deshabilitar Cancha) y el paquete GRC-21 (Gestionar Canchas). 3. Los criterios de aceptación permiten establecer posteriormente los casos de prueba asociados a cada requisito.
B18: 10 | C18: Complete | E18: OK | F18: 1. Cada requisito contiene ID, nombre, descripción, criterio de aceptación y prioridad. 2. Los criterios de aceptación especifican entradas, condiciones, restricciones y resultados esperados cuando corresponde. 3. Se contemplan las principales funcionalidades del módulo: registro, inicio de sesión, roles, control de acceso, cierre de sesión y recuperación de contraseña. | G18: OK | I18: Cada requisito funcional contiene identificador, nombre, descripción, criterio de aceptación y prioridad. Los criterios de aceptación especifican las validaciones, restricciones y resultados esperados de las operaciones del módulo. | J18: OK | K18: Cada requisito funcional contiene identificador, nombre, descripción detallada, criterios de aceptación específicos y prioridad asignada. Los criterios de aceptación especifican las validaciones, restricciones operativas, tiempos de latencia y resultados esperados ante cada operación del catálogo de canchas.
B19: 11 | C19: Understandability | E19: OK | F19: 1. Los requisitos están redactados de forma comprensible y estructurada. 2. Los nombres de las funcionalidades permiten identificar claramente el propósito de cada requisito. 3. Los criterios de aceptación utilizan condiciones concretas que facilitan la comprensión por parte del cliente, desarrolladores y equipo de pruebas. 4.Existe glosario de términos. | G19: OK | I19: Los requisitos están redactados de manera comprensible y estructurada para identificar el propósito de cada funcionalidad. Los nombres de los requisitos permiten reconocer las operaciones de gestión de productos, inventario y categorías. | J19: OK | K19: Los requisitos están redactados de manera comprensible y estructurada para identificar el propósito de cada funcionalidad. Los nombres y descripciones permiten reconocer con claridad las operaciones de registro, edición, disponibilidad y supervisión temporal de canchas. Se respalda el vocabulario en el glosario de términos del proyecto.

Sheet MODELO LIST COMPROBACION - 10.1
B1: SISTEMA: | C1: Canchas Don Pepito
B2: FECHA: | C2: 46299
B3: AUTOR: | C3: Victoria Díaz
B4: REQUERIMIENTOS EVALUADOS : | C4: 10.1 Módulo Usuarios y Autenticación
A6: CONTENIDO
A7: No. | B7: Pregunta | C7: SI | D7: NO
A8: 1 | B8: Todos los requerimientos relevantes se han documentado? | C8: X
A9: 2 | B9: Se han implementado las funciones requeridas? | D9: x
A10: 3 | B10: Existe algún mecanismo que permita seguir el impacto de dicho requerimiento a lo largo del resto de las actividades del ciclo productivo.? | D10: x
A11: 4 | B11: El origen de cada requerimento individual está claro ? | D11: x
A12: 5 | B12: Que tan facil es devolverse a los requerimientos? | C12: X
A13: 6 | B13: Los requerimientos reflejan las necesidades y deseos del cliente? | C13: X
A14: 7 | B14: No hay contradicciones entre los requerimientos? | C14: X
A15: 8 | B15: El requerimiento que se esta especificando contribuye a alcanzar un objetivo definido ? | C15: X
A16: 9 | B16: Existe un proceso acotado (en plazo y presupuesto) que permita determinar que el sistema construido satisface lo descrito en el propio requerimiento? | D16: X
A17: SUMATORIA: | C17: =COUNTA('MODELO LIST COMPROBACION - 10.1'!$C$8:$C$16) -> 5 | D17: =COUNTA('MODELO LIST COMPROBACION - 10.1'!$D$8:$D$16) -> 4
A18: PORCENTAJE : | C18: =C17/9 -> 0.55555556 | D18: =D17/9 -> 0.44444444
A20: DOCUMENTACIÓN
A21: No. | B21: Pregunta | C21: SI | D21: NO
A22: 1 | B22: Aplica un estandar para la documetación de requerimiento? | C22: X
A23: 2 | B23: Cumple con la estructura definida por el estandar? | C23: X
A24: 3 | B24: Utiliza un Glosario de términos normalizado? | C24: X
A25: 4 | B25: Los requerimientos Funcionales estan sujetos a una única interpretación? | C25: X
A26: 5 | B26: El modelo aplicado cumple con la sintaxis? | C26: X
A27: SUMATORIA: | C27: =COUNTA('MODELO LIST COMPROBACION - 10.1'!$C$22:$C$26) -> 5 | D27: =COUNTA('MODELO LIST COMPROBACION - 10.1'!$D$22:$D$26) -> 0
A28: PORCENTAJE : | C28: =C27/5 -> 1 | D28: =D27/5 -> 0
A30: NIVEL DE ACUERDO
A31: No. | B31: Pregunta | C31: SI | D31: NO
A32: 1 | B32: Todos los requerimientos han sido acordados con todos los interesados? | C32: X
A33: 2 | B33: Todos los requerimientos modificados han sido acordados por todos los implicados? | C33: X
A34: 3 | B34: Han sido resueltos todos los conflictos conocidos respectos de los requerimientos? | D34: x
A35: SUMATORIA: | C35: =COUNTA('MODELO LIST COMPROBACION - 10.1'!$C$32:$C$34) -> 2 | D35: =COUNTA('MODELO LIST COMPROBACION - 10.1'!$D$32:$D$34) -> 1
A36: PORCENTAJE : | C36: =C35/3 -> 0.66666667 | D36: =D35/3 -> 0.33333333
A40: RESUMEN
B41: CONTENIDO | C41: 89
B42: DOCUMENTACIÓN | C42: 100
B43: NIVEL DE ACUERDO | C43: 100

Sheet MODELO LIST COMPROBACION - 10.2
B1: SISTEMA: | C1: Canchas Don Pepito
B2: FECHA: | C2: 46300
B3: AUTOR: | C3: Bryan Rosero
B4: REQUERIMIENTOS EVALUADOS : | C4: 10.2 Módulo Productos
A6: CONTENIDO
A7: No. | B7: Pregunta | C7: SI | D7: NO
A8: 1 | B8: Todos los requerimientos relevantes se han documentado? | C8: X
A9: 2 | B9: Se han implementado las funciones requeridas? | D9: x
A10: 3 | B10: Existe algún mecanismo que permita seguir el impacto de dicho requerimiento a lo largo del resto de las actividades del ciclo productivo.? | C10: x
A11: 4 | B11: El origen de cada requerimento individual está claro ? | D11: x
A12: 5 | B12: Que tan facil es devolverse a los requerimientos? | C12: X
A13: 6 | B13: Los requerimientos reflejan las necesidades y deseos del cliente? | C13: X
A14: 7 | B14: No hay contradicciones entre los requerimientos? | C14: X
A15: 8 | B15: El requerimiento que se esta especificando contribuye a alcanzar un objetivo definido ? | C15: X
A16: 9 | B16: Existe un proceso acotado (en plazo y presupuesto) que permita determinar que el sistema construido satisface lo descrito en el propio requerimiento? | D16: X
A17: SUMATORIA: | C17: 6 | D17: 3
A18: PORCENTAJE : | C18: =C17/9 -> 0.66666667 | D18: =D17/9 -> 0.33333333
A20: DOCUMENTACIÓN
A21: No. | B21: Pregunta | C21: SI | D21: NO
A22: 1 | B22: Aplica un estandar para la documetación de requerimiento? | C22: X
A23: 2 | B23: Cumple con la estructura definida por el estandar? | C23: X
A24: 3 | B24: Utiliza un Glosario de términos normalizado? | C24: X
A25: 4 | B25: Los requerimientos Funcionales estan sujetos a una única interpretación? | C25: X
A26: 5 | B26: El modelo aplicado cumple con la sintaxis? | C26: X
A27: SUMATORIA: | C27: =COUNTA('MODELO LIST COMPROBACION - 10.1'!$C$22:$C$26) -> 5 | D27: =COUNTA('MODELO LIST COMPROBACION - 10.1'!$D$22:$D$26) -> 0
A28: PORCENTAJE : | C28: =C27/5 -> 1 | D28: =D27/5 -> 0
A30: NIVEL DE ACUERDO
A31: No. | B31: Pregunta | C31: SI | D31: NO
A32: 1 | B32: Todos los requerimientos han sido acordados con todos los interesados? | C32: X
A33: 2 | B33: Todos los requerimientos modificados han sido acordados por todos los implicados? | D33: X
A34: 3 | B34: Han sido resueltos todos los conflictos conocidos respectos de los requerimientos? | D34: x
A35: SUMATORIA: | C35: 1 | D35: 2
A36: PORCENTAJE : | C36: =C35/3 -> 0.33333333 | D36: =D35/3 -> 0.66666667
A40: RESUMEN
B41: CONTENIDO | C41: 67
B42: DOCUMENTACIÓN | C42: 100
B43: NIVEL DE ACUERDO | C43: 33

Sheet MODELO LIST COMPROBACION - 10.3
B1: SISTEMA: | C1: Canchas Don Pepito
B2: FECHA: | C2: 46300
B3: AUTOR: | C3: Benjamín Robalino
B4: REQUERIMIENTOS EVALUADOS : | C4: 10.3 Módulo Canchas
A6: CONTENIDO
A7: No. | B7: Pregunta | C7: SI | D7: NO
A8: 1 | B8: Todos los requerimientos relevantes se han documentado? | C8: X
A9: 2 | B9: Se han implementado las funciones requeridas? | D9: x
A10: 3 | B10: Existe algún mecanismo que permita seguir el impacto de dicho requerimiento a lo largo del resto de las actividades del ciclo productivo.? | C10: x
A11: 4 | B11: El origen de cada requerimento individual está claro ? | D11: x
A12: 5 | B12: Que tan facil es devolverse a los requerimientos? | C12: X
A13: 6 | B13: Los requerimientos reflejan las necesidades y deseos del cliente? | C13: X
A14: 7 | B14: No hay contradicciones entre los requerimientos? | C14: X
A15: 8 | B15: El requerimiento que se esta especificando contribuye a alcanzar un objetivo definido ? | C15: X
A16: 9 | B16: Existe un proceso acotado (en plazo y presupuesto) que permita determinar que el sistema construido satisface lo descrito en el propio requerimiento? | D16: X
A17: SUMATORIA: | C17: 6 | D17: 3
A18: PORCENTAJE : | C18: =C17/9 -> 0.66666667 | D18: =D17/9 -> 0.33333333
A20: DOCUMENTACIÓN
A21: No. | B21: Pregunta | C21: SI | D21: NO
A22: 1 | B22: Aplica un estandar para la documetación de requerimiento? | C22: X
A23: 2 | B23: Cumple con la estructura definida por el estandar? | C23: X
A24: 3 | B24: Utiliza un Glosario de términos normalizado? | C24: X
A25: 4 | B25: Los requerimientos Funcionales estan sujetos a una única interpretación? | C25: X
A26: 5 | B26: El modelo aplicado cumple con la sintaxis? | C26: X
A27: SUMATORIA: | C27: =COUNTA('MODELO LIST COMPROBACION - 10.1'!$C$22:$C$26) -> 5 | D27: =COUNTA('MODELO LIST COMPROBACION - 10.1'!$D$22:$D$26) -> 0
A28: PORCENTAJE : | C28: =C27/5 -> 1 | D28: =D27/5 -> 0
A30: NIVEL DE ACUERDO
A31: No. | B31: Pregunta | C31: SI | D31: NO
A32: 1 | B32: Todos los requerimientos han sido acordados con todos los interesados? | C32: X
A33: 2 | B33: Todos los requerimientos modificados han sido acordados por todos los implicados? | D33: X
A34: 3 | B34: Han sido resueltos todos los conflictos conocidos respectos de los requerimientos? | D34: x
A35: SUMATORIA: | C35: 1 | D35: 2
A36: PORCENTAJE : | C36: =C35/3 -> 0.33333333 | D36: =D35/3 -> 0.66666667
A40: RESUMEN
B41: CONTENIDO | C41: 67
B42: DOCUMENTACIÓN | C42: 100
B43: NIVEL DE ACUERDO | C43: 33

Sheet RECOMENDACIONES - 10.1
A1: PREGUNTA | B1: RECOMENDACIÓN
A2: ¿Se ha incorporado los cambios sugeridos por el tutor o el cliente? | B2: Se recomienda mantener un registro formal de los cambios sugeridos por el tutor o cliente, indicando la modificación realizada y su fecha, con el fin de facilitar la verificación de que los RF-001 al RF-006 corresponden a la versión actual de los requerimientos.
A3: ¿Se mantiene la coherencia con otros requisitos del sistema y utiliza términos o definiciones de forma uniforme a lo largo del documento? | B3: Los requisitos mantienen coherencia en su estructura y terminología, y se cuenta con un glosario de términos. Se recomienda mantener este glosario actualizado conforme se incorporen nuevos términos o modificaciones en los requerimientos
A4: ¿Se han definido casos de prueba que permitan verificar, de manera objetiva y medible, el cumplimiento del requisito? | B4: Se recomienda elaborar casos de prueba asociados a cada requisito funcional, tomando como base sus criterios de aceptación, especialmente las condiciones medibles como los 5 intentos fallidos, el bloqueo de 5 minutos, el rechazo del 100 % de accesos no autorizados y la validez de 30 minutos del enlace de recuperación.
A5: ¿Todos los requerimientos han sido acordados con todos los interesados? | B5: Los requerimientos han sido acordados con los interesados; sin embargo, se recomienda conservar evidencia formal de dichos acuerdos mediante actas, minutas, registros de reuniones o mecanismos de aprobación, para facilitar su posterior verificación y trazabilidad.

Sheet RECOMENDACIONES - 10.2
A1: PREGUNTA | B1: RECOMENDACIÓN
A2: ¿Se han incorporado los cambios sugeridos por el tutor o el cliente? | B2: Se recomienda mantener un registro formal de los cambios solicitados durante la revisión del Módulo Productos, indicando la modificación realizada, su fecha y la aprobación correspondiente. Esto facilitará la verificación de que los requisitos RF-007 al RF-015 corresponden a la versión vigente.
A3: ¿Se mantiene la coherencia con otros requisitos del sistema y se utilizan términos o definiciones de forma uniforme? | B3: Los requisitos mantienen una relación funcional entre el registro de productos, la asignación de categorías y la gestión de inventario. Se recomienda conservar actualizados el glosario y las referencias entre requisitos, especialmente para las reglas de stock, la desactivación de productos y la disponibilidad del catálogo.
A4: ¿Se han definido casos de prueba que permitan verificar, de manera objetiva y medible, el cumplimiento del requisito? | B4: Se recomienda elaborar casos de prueba para cada requisito funcional, utilizando sus criterios de aceptación. Deben priorizarse la validación de campos obligatorios, la detección de productos duplicados, la actualización del inventario en menos de 2 segundos, las consultas en menos de 3 segundos y las alertas de stock mínimo en un máximo de 1 minuto. También deben probarse las ventas concurrentes y la reversión de existencias ante anulaciones.
A5: ¿Todos los requerimientos han sido acordados con todos los interesados? | B5: Se recomienda conservar evidencia formal de la revisión y aprobación de los requisitos RF-007 al RF-015 por parte del cliente o responsable del proyecto, mediante actas, minutas o registros de validación. Esto permitirá demostrar el nivel de acuerdo y facilitar la resolución de posibles conflictos.

Sheet RECOMENDACIONES - 10.3
A1: PREGUNTA | B1: RECOMENDACIÓN
A2: ¿Se han incorporado los cambios sugeridos por el tutor o el cliente? | B2: Se recomienda mantener un registro formal de los cambios solicitados durante la revisión del Módulo Canchas, indicando la modificación realizada (en especial respecto a las reglas de cambio de tarifa sobre reservas previas y políticas de horarios de atención), su fecha y la aprobación correspondiente del cliente. Esto facilitará la verificación de que los requisitos RF-016 al RF-020 corresponden a la versión vigente.
A3: ¿Se mantiene la coherencia con otros requisitos del sistema y se utilizan términos o definiciones de forma uniforme? | B3: Los requisitos mantienen una relación funcional coherente entre la administración de canchas, el calendario de disponibilidad visual y la gestión de reservas activas. Se recomienda conservar actualizados el glosario de términos y las referencias cruzadas entre requisitos, unificando definiciones clave como tarifa por hora, horario de atención, cancha disponible/deshabilitada y alerta de tiempo límite, garantizando que las métricas de latencia (5 s en catálogo y 3 s en calendario) se interpreten de forma homogénea.
A4: ¿Se han definido casos de prueba que permitan verificar, de manera objetiva y medible, el cumplimiento del requisito? | B4: Se recomienda elaborar casos de prueba para cada requisito funcional del módulo, utilizando sus criterios de aceptación medibles. Deben priorizarse: 1) Validación de campos obligatorios e integridad en el registro de canchas (RF-016); 2) Verificación de reflejo de modificaciones en menos de 5 segundos y no afectación de tarifas previas en reservas confirmadas (RF-017); 3) Medición de latencia menor o igual a 3 segundos en la actualización del calendario visual bajo concurrencia (RF-018); 4) Deshabilitación inmediata en catálogo y emisión de notificaciones a clientes afectados (RF-019); y 5) Disparo automático de la alerta a los 10 minutos restantes con margen de error inferior a 30 segundos y resiliencia tras pérdida de conexión (RF-020).
A5: ¿Todos los requerimientos han sido acordados con todos los interesados? | B5: Se recomienda conservar evidencia formal de la revisión y aprobación de los requisitos RF-016 al RF-020 por parte del dueño del negocio (Canchas Don Pepito) y el responsable del proyecto, mediante actas de reunión, minutas firmadas o registros de validación del prototipo. Esto permitirá demostrar el nivel de acuerdo y sustentar la resolución formal de posibles conflictos en las reglas operativas del módulo.
